test_package/__init__.py
test_package/test_module.py
sphinx_readme_test_package-1.0.0.dist-info/METADATA
sphinx_readme_test_package-1.0.0.dist-info/WHEEL
sphinx_readme_test_package-1.0.0.dist-info/top_level.txt
sphinx_readme_test_package-1.0.0.dist-info/RECORD
